packpypi/__init__.py
packpypi/armazenamento.py
packpypi/consulta.py
packpypi/interacao.py
packpypi-0.0.1.dist-info/LICENSE.txt
packpypi-0.0.1.dist-info/METADATA
packpypi-0.0.1.dist-info/WHEEL
packpypi-0.0.1.dist-info/top_level.txt
packpypi-0.0.1.dist-info/RECORD
