Metadata-Version: 2.1
Name: packpypi
Version: 0.0.1
Summary: Pacote python para estudar python
Home-page: http://github.com
Author: Pedro Vitor Raiol Comin
Author-email: pedro21070007@aluno.cesupa.br
License: MIT License
Keywords: Pacote
Platform: UNKNOWN
License-File: LICENSE.txt
